Metadata-Version: 2.1
Name: kpi-formula-jun
Version: 0.2.6
Summary: A KPI calculation tool
Home-page: https://github.com/leoren1314/kpi-formula
Author: Jun Ren
Author-email: leoren1314@gmail.com
Project-URL: Bug Reports, https://github.com/yourusername/kpi-formula/issues
Project-URL: Source, https://github.com/yourusername/kpi-formula
Classifier: Development Status :: 3 - Alpha
Classifier: Intended Audience :: Developers
Classifier: License :: OSI Approved :: MIT License
Classifier: Operating System :: OS Independent
Classifier: Programming Language :: Python :: 3
Classifier: Programming Language :: Python :: 3.7
Classifier: Programming Language :: Python :: 3.8
Classifier: Programming Language :: Python :: 3.9
Requires-Python: >=3.7
License-File: LICENSE
Requires-Dist: pandas>=1.0.0
Requires-Dist: numpy>=1.18.0
Requires-Dist: statistics
Requires-Dist: flask>=2.0.0
